pyfeversmart/__init__.py
pyfeversmart/fever_smart.py
pyfeversmart-0.1.0.dist-info/METADATA
pyfeversmart-0.1.0.dist-info/WHEEL
pyfeversmart-0.1.0.dist-info/licenses/LICENSE
pyfeversmart-0.1.0.dist-info/RECORD
